outlier/__init__.py
outlier/outlier.py
outlier-0.2.dist-info/LICENSE
outlier-0.2.dist-info/METADATA
outlier-0.2.dist-info/WHEEL
outlier-0.2.dist-info/top_level.txt
outlier-0.2.dist-info/RECORD
