Metadata-Version: 2.1
Name: outlier
Version: 0.2
Summary: outlier
Home-page: https://github.com/archongum/outlier
Author: archon
Author-email: qq349074225@live.com
License: apache
Platform: UNKNOWN
Classifier: Development Status :: 3 - Alpha
Classifier: License :: OSI Approved :: Apache Software License
Classifier: Programming Language :: Python :: 2
Classifier: Programming Language :: Python :: 3
Requires-Dist: numpy
